{"metadata": {"dbt_schema_version": "https://schemas.getdbt.com/dbt/catalog/v1.json", "dbt_version": "1.10.11", "generated_at": "2025-09-20T12:12:10.503643Z", "invocation_id": "2b541ff2-5428-44f9-a469-20a5548c574b", "invocation_started_at": "2025-09-20T12:12:06.104312Z", "env": {}}, "nodes": {"seed.vg_casestudy.dbt_project_evaluator_exceptions": {"metadata": {"type": "BASE TABLE", "schema": "public", "name": "dbt_project_evaluator_exceptions", "database": "postgres", "comment": null, "owner": "postgres"}, "columns": {"fct_name": {"type": "text", "index": 1, "name": "fct_name", "comment": null}, "column_name": {"type": "text", "index": 2, "name": "column_name", "comment": null}, "id_to_exclude": {"type": "text", "index": 3, "name": "id_to_exclude", "comment": null}, "comment": {"type": "text", "index": 4, "name": "comment", "comment": null}}, "stats": {"has_stats": {"id": "has_stats", "label": "Has Stats?", "value": false, "include": false, "description": "Indicates whether there are statistics for this table"}}, "unique_id": "seed.vg_casestudy.dbt_project_evaluator_exceptions"}, "model.vg_casestudy.report": {"metadata": {"type": "BASE TABLE", "schema": "reporting", "name": "report", "database": "postgres", "comment": null, "owner": "postgres"}, "columns": {"account_id": {"type": "integer", "index": 1, "name": "account_id", "comment": null}, "customer_id": {"type": "integer", "index": 2, "name": "customer_id", "comment": null}, "account_type": {"type": "character varying", "index": 3, "name": "account_type", "comment": null}, "account_opening_date": {"type": "date", "index": 4, "name": "account_opening_date", "comment": null}}, "stats": {"has_stats": {"id": "has_stats", "label": "Has Stats?", "value": false, "include": false, "description": "Indicates whether there are statistics for this table"}}, "unique_id": "model.vg_casestudy.report"}, "model.vg_casestudy.stg_raw_staging__accounts": {"metadata": {"type": "VIEW", "schema": "staging", "name": "stg_raw_staging__accounts", "database": "postgres", "comment": null, "owner": "postgres"}, "columns": {"account_id": {"type": "integer", "index": 1, "name": "account_id", "comment": null}, "customer_id": {"type": "integer", "index": 2, "name": "customer_id", "comment": null}, "account_type": {"type": "character varying", "index": 3, "name": "account_type", "comment": null}, "account_opening_date": {"type": "date", "index": 4, "name": "account_opening_date", "comment": null}}, "stats": {"has_stats": {"id": "has_stats", "label": "Has Stats?", "value": false, "include": false, "description": "Indicates whether there are statistics for this table"}}, "unique_id": "model.vg_casestudy.stg_raw_staging__accounts"}, "model.vg_casestudy.stg_raw_staging__customers": {"metadata": {"type": "VIEW", "schema": "staging", "name": "stg_raw_staging__customers", "database": "postgres", "comment": null, "owner": "postgres"}, "columns": {"customer_id": {"type": "integer", "index": 1, "name": "customer_id", "comment": null}, "firstname": {"type": "character varying", "index": 2, "name": "firstname", "comment": null}, "lastname": {"type": "character varying", "index": 3, "name": "lastname", "comment": null}, "age": {"type": "integer", "index": 4, "name": "age", "comment": null}}, "stats": {"has_stats": {"id": "has_stats", "label": "Has Stats?", "value": false, "include": false, "description": "Indicates whether there are statistics for this table"}}, "unique_id": "model.vg_casestudy.stg_raw_staging__customers"}, "model.vg_casestudy.stg_raw_staging__fx_rates": {"metadata": {"type": "VIEW", "schema": "staging", "name": "stg_raw_staging__fx_rates", "database": "postgres", "comment": null, "owner": "postgres"}, "columns": {"currency_iso_code": {"type": "character varying", "index": 1, "name": "currency_iso_code", "comment": null}, "fx_rate": {"type": "character varying", "index": 2, "name": "fx_rate", "comment": null}, "fx_rate_date": {"type": "date", "index": 3, "name": "fx_rate_date", "comment": null}}, "stats": {"has_stats": {"id": "has_stats", "label": "Has Stats?", "value": false, "include": false, "description": "Indicates whether there are statistics for this table"}}, "unique_id": "model.vg_casestudy.stg_raw_staging__fx_rates"}, "model.vg_casestudy.stg_raw_staging__transactions": {"metadata": {"type": "VIEW", "schema": "staging", "name": "stg_raw_staging__transactions", "database": "postgres", "comment": null, "owner": "postgres"}, "columns": {"transaction_id": {"type": "integer", "index": 1, "name": "transaction_id", "comment": null}, "transaction_date": {"type": "character varying", "index": 2, "name": "transaction_date", "comment": null}, "account_id": {"type": "integer", "index": 3, "name": "account_id", "comment": null}, "transaction_type": {"type": "character varying", "index": 4, "name": "transaction_type", "comment": null}, "transaction_amount": {"type": "character varying", "index": 5, "name": "transaction_amount", "comment": null}, "transaction_currency": {"type": "character varying", "index": 6, "name": "transaction_currency", "comment": null}}, "stats": {"has_stats": {"id": "has_stats", "label": "Has Stats?", "value": false, "include": false, "description": "Indicates whether there are statistics for this table"}}, "unique_id": "model.vg_casestudy.stg_raw_staging__transactions"}}, "sources": {"source.vg_casestudy.raw.accounts": {"metadata": {"type": "BASE TABLE", "schema": "raw", "name": "accounts", "database": "postgres", "comment": null, "owner": "postgres"}, "columns": {"account_id": {"type": "integer", "index": 1, "name": "account_id", "comment": null}, "customer_id": {"type": "integer", "index": 2, "name": "customer_id", "comment": null}, "account_type": {"type": "character varying", "index": 3, "name": "account_type", "comment": null}, "account_opening_date": {"type": "character varying", "index": 4, "name": "account_opening_date", "comment": null}}, "stats": {"has_stats": {"id": "has_stats", "label": "Has Stats?", "value": false, "include": false, "description": "Indicates whether there are statistics for this table"}}, "unique_id": "source.vg_casestudy.raw.accounts"}, "source.vg_casestudy.raw.customers": {"metadata": {"type": "BASE TABLE", "schema": "raw", "name": "customers", "database": "postgres", "comment": null, "owner": "postgres"}, "columns": {"customer_id": {"type": "integer", "index": 1, "name": "customer_id", "comment": null}, "firstname": {"type": "character varying", "index": 2, "name": "firstname", "comment": null}, "lastname": {"type": "character varying", "index": 3, "name": "lastname", "comment": null}, "Age": {"type": "integer", "index": 4, "name": "Age", "comment": null}, "Gender": {"type": "character varying", "index": 5, "name": "Gender", "comment": null}, "Address": {"type": "character varying", "index": 6, "name": "Address", "comment": null}, "City": {"type": "character varying", "index": 7, "name": "City", "comment": null}, "Contact Number": {"type": "bigint", "index": 8, "name": "Contact Number", "comment": null}, "Email": {"type": "character varying", "index": 9, "name": "Email", "comment": null}, "creation_date": {"type": "character varying", "index": 10, "name": "creation_date", "comment": null}, "branch_id": {"type": "integer", "index": 11, "name": "branch_id", "comment": null}}, "stats": {"has_stats": {"id": "has_stats", "label": "Has Stats?", "value": false, "include": false, "description": "Indicates whether there are statistics for this table"}}, "unique_id": "source.vg_casestudy.raw.customers"}, "source.vg_casestudy.raw.fx_rates": {"metadata": {"type": "BASE TABLE", "schema": "raw", "name": "fx_rates", "database": "postgres", "comment": null, "owner": "postgres"}, "columns": {"currency_iso_code": {"type": "character varying", "index": 1, "name": "currency_iso_code", "comment": null}, "fx_rate": {"type": "character varying", "index": 2, "name": "fx_rate", "comment": null}, "date": {"type": "character varying", "index": 3, "name": "date", "comment": null}, "Column4": {"type": "character varying", "index": 4, "name": "Column4", "comment": null}}, "stats": {"has_stats": {"id": "has_stats", "label": "Has Stats?", "value": false, "include": false, "description": "Indicates whether there are statistics for this table"}}, "unique_id": "source.vg_casestudy.raw.fx_rates"}, "source.vg_casestudy.raw.loans": {"metadata": {"type": "BASE TABLE", "schema": "raw", "name": "loans", "database": "postgres", "comment": null, "owner": "postgres"}, "columns": {"customer_id": {"type": "integer", "index": 1, "name": "customer_id", "comment": null}, "loan_id": {"type": "integer", "index": 2, "name": "loan_id", "comment": null}, "loan_amount": {"type": "character varying", "index": 3, "name": "loan_amount", "comment": null}, "loant_type": {"type": "character varying", "index": 4, "name": "loant_type", "comment": null}, "interest_rate": {"type": "character varying", "index": 5, "name": "interest_rate", "comment": null}, "loan_term": {"type": "integer", "index": 6, "name": "loan_term", "comment": null}, "approval_rejection_date": {"type": "character varying", "index": 7, "name": "approval_rejection_date", "comment": null}, "loan_status": {"type": "character varying", "index": 8, "name": "loan_status", "comment": null}}, "stats": {"has_stats": {"id": "has_stats", "label": "Has Stats?", "value": false, "include": false, "description": "Indicates whether there are statistics for this table"}}, "unique_id": "source.vg_casestudy.raw.loans"}, "source.vg_casestudy.raw.transactions": {"metadata": {"type": "BASE TABLE", "schema": "raw", "name": "transactions", "database": "postgres", "comment": null, "owner": "postgres"}, "columns": {"transaction_id": {"type": "integer", "index": 1, "name": "transaction_id", "comment": null}, "transaction_date": {"type": "character varying", "index": 2, "name": "transaction_date", "comment": null}, "account_id": {"type": "integer", "index": 3, "name": "account_id", "comment": null}, "transaction_type": {"type": "character varying", "index": 4, "name": "transaction_type", "comment": null}, "transaction_amount": {"type": "character varying", "index": 5, "name": "transaction_amount", "comment": null}, "transaction_currency": {"type": "character varying", "index": 6, "name": "transaction_currency", "comment": null}}, "stats": {"has_stats": {"id": "has_stats", "label": "Has Stats?", "value": false, "include": false, "description": "Indicates whether there are statistics for this table"}}, "unique_id": "source.vg_casestudy.raw.transactions"}}, "errors": null}